JovQueue/__init__.py
jovqueue-1.0.0.dist-info/METADATA
jovqueue-1.0.0.dist-info/WHEEL
jovqueue-1.0.0.dist-info/licenses/LICENSE
jovqueue-1.0.0.dist-info/RECORD
