Metadata-Version: 2.3
Name: JovQueue
Version: 1.0.0
Summary: An easy to use module for turning functions into daemons with queueing capabilities.
Project-URL: Homepage, https://github.com/jwburke02/JovQueue
Project-URL: Issues, https://github.com/jwburke02/JovQueue/issues
Author-email: John Burke <jwburke2002@gmail.com>
License-File: LICENSE
Classifier: License :: OSI Approved :: MIT License
Classifier: Operating System :: OS Independent
Classifier: Programming Language :: Python :: 3
Requires-Python: >=3.8
